dionn/__init__.py
dionn/data_selector.py
utils/__init__.py
dionn-1.6.0.dist-info/METADATA
dionn-1.6.0.dist-info/WHEEL
dionn-1.6.0.dist-info/top_level.txt
dionn-1.6.0.dist-info/RECORD
