Metadata-Version: 2.4
Name: dionn
Version: 1.6.0
Summary: Detection Intra-class Outliers with Neural Networks (DIONN) algorithm
Home-page: https://github.com/juanzamorai/intracluster-filtering
Author: Juan Zamora, Sebastian Vegas, Kerlyns Martínez, Daira Velandia, Sebastián Jara, Pascal Sigel
Author-email: 
License: MIT
Dynamic: author
Dynamic: description
Dynamic: description-content-type
Dynamic: home-page
Dynamic: license
Dynamic: summary
